llama_index/packs/llama_guard_moderator/__init__.py
llama_index/packs/llama_guard_moderator/base.py
llama_index_packs_llama_guard_moderator-0.4.1.dist-info/METADATA
llama_index_packs_llama_guard_moderator-0.4.1.dist-info/WHEEL
llama_index_packs_llama_guard_moderator-0.4.1.dist-info/licenses/LICENSE
llama_index_packs_llama_guard_moderator-0.4.1.dist-info/RECORD
