Metadata-Version: 2.4
Name: llama-index-packs-llama-guard-moderator
Version: 0.4.1
Summary: llama-index packs llama_guard_moderator integration
Author-email: Your Name <you@example.com>
Maintainer: wenqiglantz
License-Expression: MIT
License-File: LICENSE
Keywords: llama guard,llm security,prompt injection,purple llama
Requires-Python: <4.0,>=3.9
Requires-Dist: accelerate<0.27,>=0.26.1
Requires-Dist: llama-index-core<0.15,>=0.13.0
Requires-Dist: torch<3,>=2.1.2
Requires-Dist: transformers<5,>=4.37.1
